nlp/__init__.py
nlp/client.py
nlp/constants.py
nlp/models.py
nlp_sdk-1.0.2.dist-info/METADATA
nlp_sdk-1.0.2.dist-info/WHEEL
nlp_sdk-1.0.2.dist-info/top_level.txt
nlp_sdk-1.0.2.dist-info/RECORD
